{
    "brandsArabic": [
        {
            "name":  "تويوتا",
            "icon": "/imgs/brands/toyota.png"
        },
        {
            "name": "فورد",
            "icon": "/imgs/brands/ford.png"
        },
        {
            "name": "جي ام سي",
            "icon": "/imgs/brands/gmc.png"
        },
        {
            "name":"شيفروليه",
            "icon": "/imgs/brands/chevrolet.png"
        },
        {
            "name": "نيسان",
            "icon": "/imgs/brands/nissan.png"
        },
        {
            "name":"دودج",
            "icon": "/imgs/brands/dodge.png"
        },
        {
            "name":"كرايلزر",
            "icon": "/imgs/brands/chrysler.png"
        },
        {
            "name":  "لكزس",
            "icon": "/imgs/brands/lexus.png"
        },
       
        "بيجو",
        "لينكولن",
        "كاديلاك",
        "هوندا",
        "جيب",
        "هيونداي",
        "فيات",
        "شيري",
        "شانجان",
        "سوبارو",
        "ام جي",
        "فاو",
        "رام",
        "جينيسيس"
    ],
    "modelsArabic": {
        "تويوتا":[
            "كامري",
            "افالون",
            "اينوفا",
            "هايس",
            "برادو",
            "بريفيا",
            "راف باور",
            "سيكويا",
            "سوبرا",
            "فورشنر",
            "كورلا",
            "لاند كروزر",
            "يارس",
            "هايلاندر",
            "هايلوكس",
            "شاص",
            "ربع",
            "اف جي",
            "تندرا",
            "افانزا",
            "اوريون",
            "بيريوس",
            "راش"
        ],

    }
}